pyrandomorg/Pyrandomorg.py
pyrandomorg/__init__.py
Pyrandomorg-0.0.2.dist-info/LICENSE
Pyrandomorg-0.0.2.dist-info/METADATA
Pyrandomorg-0.0.2.dist-info/WHEEL
Pyrandomorg-0.0.2.dist-info/top_level.txt
Pyrandomorg-0.0.2.dist-info/RECORD
