Metadata-Version: 2.1
Name: Pyrandomorg
Version: 0.0.2
Summary: Simple Asynchronous Python Library For Random.org API
Home-page: https://github.com/AlexanderVolkov22/pyrandomorg
Author: AlexanderVolkov22
Author-email: alexanderedit22@gmail.com
License: UNKNOWN
Platform: UNKNOWN
Classifier: Programming Language :: Python :: 3.8
Classifier: License :: OSI Approved :: MIT License
Classifier: Operating System :: OS Independent
Requires-Python: >=3.8
Requires-Dist: requests (<=2.21.0)
Requires-Dist: aiohttp (<=3.7.3)
